[
  {
    "createTime": 1597041160327,
    "rank": 0,
    "createMember": {
      "name": "宗传奇"
    },
    "lastUpdateTime": 1597041160327,
    "lastUpdateMember": {
      "name": "宗传奇"
    },
    "siteId": "730699648670371840",
    "display": true,
    "name": "新冠疫情对汽车经销行业影响的调查数据（第一版）",
    "publishTime": 1596263466320,
    "_id": "742269167922581504",
    "_javaMetaTypeHashCode": -1070231945,
    "mid": "742269167922581504",
    "attachment": [
      {
        "url": "https://static.onepushing.com/10717/742269159085182976.txt",
        "name": ""
      }
    ]
  },
  {
    "createTime": 1597041193400,
    "rank": 0,
    "createMember": {
      "name": "宗传奇"
    },
    "lastUpdateTime": 1597041193400,
    "lastUpdateMember": {
      "name": "宗传奇"
    },
    "siteId": "730699648670371840",
    "display": true,
    "name": "新冠疫情对汽车经销行业影响的调查数据（第二版）",
    "publishTime": 1596609191370,
    "_id": "742269306640797696",
    "_javaMetaTypeHashCode": -1070231945,
    "mid": "742269306640797696",
    "attachment": [
      {
        "url": "https://static.onepushing.com/10717/742269296553496576.txt",
        "name": ""
      }
    ]
  },
  {
    "createTime": 1597041275800,
    "rank": 0,
    "createMember": {
      "name": "宗传奇"
    },
    "lastUpdateTime": 1597041275800,
    "lastUpdateMember": {
      "name": "宗传奇"
    },
    "siteId": "730699648670371840",
    "display": true,
    "name": "新冠疫情对汽车经销行业影响的调查数据（第一版）",
    "publishTime": 1597905272438,
    "_id": "742269652251447296",
    "_javaMetaTypeHashCode": -1070231945,
    "mid": "742269652251447296",
    "attachment": [
      {
        "url": "https://static.onepushing.com/10717/742269636401172480.txt",
        "name": ""
      }
    ]
  },
  {
    "createTime": 1597041284047,
    "rank": 0,
    "createMember": {
      "name": "宗传奇"
    },
    "lastUpdateTime": 1597041284047,
    "lastUpdateMember": {
      "name": "宗传奇"
    },
    "siteId": "730699648670371840",
    "display": true,
    "name": "新冠疫情对汽车经销行业影响的调查数据（第一版）",
    "publishTime": 1595918078385,
    "_id": "742269686841872384",
    "_javaMetaTypeHashCode": -1070231945,
    "mid": "742269686841872384",
    "attachment": [
      {
        "url": "https://static.onepushing.com/10717/742269682773397504.txt",
        "name": ""
      }
    ]
  },
  {
    "createTime": 1597041292644,
    "rank": 0,
    "createMember": {
      "name": "宗传奇"
    },
    "lastUpdateTime": 1597041292644,
    "lastUpdateMember": {
      "name": "宗传奇"
    },
    "siteId": "730699648670371840",
    "display": true,
    "name": "新冠疫情对汽车经销行业影响的调查数据（第一版）",
    "publishTime": 1597127686755,
    "_id": "742269722900303872",
    "_javaMetaTypeHashCode": -1070231945,
    "mid": "742269722900303872",
    "attachment": [
      {
        "url": "https://static.onepushing.com/10717/742269719351922688.txt",
        "name": ""
      }
    ]
  },
  {
    "createTime": 1597041300080,
    "rank": 0,
    "createMember": {
      "name": "宗传奇"
    },
    "lastUpdateTime": 1597041300080,
    "lastUpdateMember": {
      "name": "宗传奇"
    },
    "siteId": "730699648670371840",
    "display": true,
    "name": "新冠疫情对汽车经销行业影响的调查数据（第一版）",
    "publishTime": 1596868495377,
    "_id": "742269754089148416",
    "_javaMetaTypeHashCode": -1070231945,
    "mid": "742269754089148416",
    "attachment": [
      {
        "url": "https://static.onepushing.com/10717/742269750599487488.txt",
        "name": ""
      }
    ]
  },
  {
    "createTime": 1597041309285,
    "rank": 0,
    "createMember": {
      "name": "宗传奇"
    },
    "lastUpdateTime": 1597041309285,
    "lastUpdateMember": {
      "name": "宗传奇"
    },
    "siteId": "730699648670371840",
    "display": true,
    "name": "新冠疫情对汽车经销行业影响的调查数据（第一版）",
    "publishTime": 1596263703154,
    "_id": "742269792697716736",
    "_javaMetaTypeHashCode": -1070231945,
    "mid": "742269792697716736",
    "attachment": [
      {
        "url": "https://static.onepushing.com/10717/742269788281114624.txt",
        "name": ""
      }
    ]
  },
  {
    "createTime": 1597041320520,
    "rank": 0,
    "createMember": {
      "name": "宗传奇"
    },
    "lastUpdateTime": 1597041320520,
    "lastUpdateMember": {
      "name": "宗传奇"
    },
    "siteId": "730699648670371840",
    "display": true,
    "name": "新冠疫情对汽车经销行业影响的调查数据（第一版）",
    "publishTime": 1596868514875,
    "_id": "742269839820722176",
    "_javaMetaTypeHashCode": -1070231945,
    "mid": "742269839820722176",
    "attachment": [
      {
        "url": "https://static.onepushing.com/10717/742269836683382784.txt",
        "name": ""
      }
    ]
  },
  {
    "createTime": 1597041328888,
    "rank": 0,
    "createMember": {
      "name": "宗传奇"
    },
    "lastUpdateTime": 1597041328888,
    "lastUpdateMember": {
      "name": "宗传奇"
    },
    "siteId": "730699648670371840",
    "display": true,
    "name": "新冠疫情对汽车经销行业影响的调查数据（第一版）",
    "publishTime": 1598596524329,
    "_id": "742269874918658048",
    "_javaMetaTypeHashCode": -1070231945,
    "mid": "742269874918658048",
    "attachment": [
      {
        "url": "https://static.onepushing.com/10717/742269871957479424.txt",
        "name": ""
      }
    ]
  },
  {
    "createTime": 1597041340957,
    "rank": 0,
    "createMember": {
      "name": "宗传奇"
    },
    "lastUpdateTime": 1597041340957,
    "lastUpdateMember": {
      "name": "宗传奇"
    },
    "siteId": "730699648670371840",
    "display": true,
    "name": "新冠疫情对汽车经销行业影响的调查数据（第一版）",
    "publishTime": 1596695733080,
    "_id": "742269925539713024",
    "_javaMetaTypeHashCode": -1070231945,
    "mid": "742269925539713024",
    "attachment": [
      {
        "url": "https://static.onepushing.com/10717/742269922725335040.txt",
        "name": ""
      }
    ]
  },
  {
    "createTime": 1597041349957,
    "rank": 0,
    "createMember": {
      "name": "宗传奇"
    },
    "lastUpdateTime": 1597041349957,
    "lastUpdateMember": {
      "name": "宗传奇"
    },
    "siteId": "730699648670371840",
    "display": true,
    "name": "新冠疫情对汽车经销行业影响的调查数据（第一版）",
    "_id": "742269963288449024",
    "_javaMetaTypeHashCode": -1070231945,
    "mid": "742269963288449024",
    "attachment": [
      {
        "url": "https://static.onepushing.com/10717/742269960490848256.txt",
        "name": ""
      }
    ]
  }
]